Metadata-Version: 1.1
Name: featuremonkey
Version: 0.3.1
Summary: FOP for Python
Home-page: http://github.com/henzk/featuremonkey
Author: Hendrik Speidel
Author-email: hendrik@schnapptack.de
License: MIT License
Keywords: fop,features,program composition,program synthesis,monkey-patching
Platform: UNKNOWN
Classifier: License :: OSI Approved :: MIT License
Classifier: Programming Language :: Python
Classifier: Intended Audience :: Developers
Classifier: Operating System :: OS Independent
